task_status/__init__.py
task_status/task_status.py
task_status-0.4.1.dist-info/METADATA
task_status-0.4.1.dist-info/WHEEL
task_status-0.4.1.dist-info/entry_points.txt
task_status-0.4.1.dist-info/RECORD
